{
  "_id": "2EUaqXQZMI4y29XN",
  "name": "ACPA SCATTER PACKS BSP Smoke Pellets HVY +3 N",
  "type": "weapon",
  "img": "icons/svg/mystery-man.svg",
  "data": {
    "flavor": "",
    "notes": "",
    "source": "MM",
    "cost": 300.0,
    "weight": 1,
    "attackType": "Auto",
    "weaponType": "Pistol",
    "accuracy": "5",
    "concealability": "min",
    "availability": null,
    "ammoType": null,
    "damage": "cloud",
    "shots": "1x50",
    "rof": "1d6",
    "reliability": "VR",
    "range": "50m"
  },
  "effects": [],
  "flags": {
    "exportSource": {
      "world": "cyberpunk_2020",
      "system": "cyberpunk2020-rilerena",
      "coreVersion": "0.7.9",
      "systemVersion": "0.2.6"
    }
  }
}