{
  "_id": "yEqB4jgcshtkZNM9",
  "name": "Baretta M20-F",
  "type": "weapon",
  "img": "icons/svg/mystery-man.svg",
  "data": {
    "flavor": "",
    "notes": "",
    "source": "P1",
    "cost": 750.0,
    "weight": 1,
    "weaponType": "P",
    "accuracy": "+1",
    "concealability": "J",
    "availability": "C",
    "ammoType": null,
    "damage": "3d6+3",
    "shots": "15",
    "rof": "3",
    "reliability": "VR",
    "range": "50m",
    "attackType": "Auto"
  },
  "effects": [],
  "flags": {
    "exportSource": {
      "world": "cyberpunk_2020",
      "system": "cyberpunk2020-rilerena",
      "coreVersion": "0.7.9",
      "systemVersion": "0.2.6"
    }
  }
}