{
  "_id": "bWhN3owq3ci5Bfxn",
  "name": "Bell Spy-Eye 18",
  "type": "vehicle",
  "img": "icons/svg/mystery-man.svg",
  "data": {
    "flavor": "",
    "notes": "<b>Top Speed:</b> 180<br><b>Acc/Dec:</b> 15/15<br><b>Crew:</b> 1<br><b>Range:</b> 400<br><b>Passengers:</b> 3<br><b>Cargo:</b> 2000kg<br><b>Maneuver:</b> +2<br><b>SDP:</b> 65 (3)<br><b>SP:</b> 12<br><b>Mass:</b> (1) 6,500kg",
    "source": "Chr1",
    "cost": 206000.0,
    "weight": 1
  },
  "effects": [],
  "flags": {
    "exportSource": {
      "world": "cyberpunk_2020",
      "system": "cyberpunk2020-rilerena",
      "coreVersion": "0.7.9",
      "systemVersion": "0.2.6"
    }
  }
}