{
  "_id": "FJN9GFovFCGxQfIZ",
  "name": "GMI Sierra GL",
  "type": "vehicle",
  "img": "icons/svg/mystery-man.svg",
  "data": {
    "flavor": "",
    "notes": "<b>Top Speed:</b> 70<br><b>Acc/Dec:</b> 15/50<br><b>Crew:</b> 1<br><b>Range:</b> 300<br><b>Passengers:</b> 3<br><b>Cargo:</b> 453kg<br><b>Maneuver:</b> +0<br><b>SDP:</b> 34 (2)<br><b>SP:</b> 10<br><b>Mass:</b> (0) 1360kg",
    "source": "Chr4",
    "cost": 20350.0,
    "weight": 1
  },
  "effects": [],
  "flags": {
    "exportSource": {
      "world": "cyberpunk_2020",
      "system": "cyberpunk2020-rilerena",
      "coreVersion": "0.7.9",
      "systemVersion": "0.2.6"
    }
  }
}