{
  "_id": "OFVI9OpBW46qFpfg",
  "name": "Aquarius (Sub-Marine)",
  "type": "cyberware",
  "img": "icons/svg/mystery-man.svg",
  "data": {
    "flavor": "",
    "notes": "<b>Surgery Code:</b> CRx2<br><b>Humanity Loss:</b> 18d6+2<br><p>REF 10, MA 10, BOD 15, SP 25, SDP 20/30/40</p>",
    "source": "Chr2",
    "cost": 50000.0,
    "weight": 1
  },
  "effects": [],
  "flags": {
    "exportSource": {
      "world": "cyberpunk_2020",
      "system": "cyberpunk2020-rilerena",
      "coreVersion": "0.7.9",
      "systemVersion": "0.2.6"
    }
  }
}