{
  "name": "Cutting Torch",
  "permission": {
    "default": 0
  },
  "type": "cyberware",
  "data": {
    "cyberwareType": "CYBERLIMB",
    "cyberwareSubtype": "BUILTIN",
    "surgCode": "N",
    "humanityCost": "1d6/2+1",
    "notes": "",
    "flavor": "Can cut through SP20",
    "cost": 100,
    "weight": 0,
    "equipped": true,
    "slots": 0,
    "spaces": 0,
    "abbrev": "",
    "flags": {},
    "source": "Chromebook 1 pg.36"
  },
  "_id": "G84MbMxDERtsdNXr",
  "_key": "!items!G84MbMxDERtsdNXr"
}